graphsense/__init__.py
graphsense/api_client.py
graphsense/configuration.py
graphsense/exceptions.py
graphsense/model_utils.py
graphsense/rest.py
graphsense/api/__init__.py
graphsense/api/addresses_api.py
graphsense/api/blocks_api.py
graphsense/api/bulk_api.py
graphsense/api/entities_api.py
graphsense/api/general_api.py
graphsense/api/rates_api.py
graphsense/api/tags_api.py
graphsense/api/tokens_api.py
graphsense/api/txs_api.py
graphsense/apis/__init__.py
graphsense/model/__init__.py
graphsense/model/actor.py
graphsense/model/actor_context.py
graphsense/model/actors.py
graphsense/model/address.py
graphsense/model/address_tag.py
graphsense/model/address_tag_all_of.py
graphsense/model/address_tags.py
graphsense/model/address_tx.py
graphsense/model/address_tx_utxo.py
graphsense/model/address_txs.py
graphsense/model/block.py
graphsense/model/block_at_date.py
graphsense/model/concept.py
graphsense/model/currency_stats.py
graphsense/model/entity.py
graphsense/model/entity_addresses.py
graphsense/model/external_conversion.py
graphsense/model/height.py
graphsense/model/label_summary.py
graphsense/model/labeled_item_ref.py
graphsense/model/labeled_item_refs.py
graphsense/model/link.py
graphsense/model/link_utxo.py
graphsense/model/links.py
graphsense/model/neighbor_address.py
graphsense/model/neighbor_addresses.py
graphsense/model/neighbor_entities.py
graphsense/model/neighbor_entity.py
graphsense/model/rate.py
graphsense/model/rates.py
graphsense/model/related_address.py
graphsense/model/related_addresses.py
graphsense/model/search_result.py
graphsense/model/search_result_by_currency.py
graphsense/model/search_result_labels.py
graphsense/model/search_result_leaf.py
graphsense/model/search_result_level1.py
graphsense/model/search_result_level2.py
graphsense/model/search_result_level3.py
graphsense/model/search_result_level4.py
graphsense/model/search_result_level5.py
graphsense/model/search_result_level6.py
graphsense/model/stats.py
graphsense/model/tag.py
graphsense_python-1.17.0.dist-info/METADATA
graphsense_python-1.17.0.dist-info/WHEEL
graphsense_python-1.17.0.dist-info/top_level.txt
graphsense_python-1.17.0.dist-info/RECORD
