Metadata-Version: 2.4
Name: graphsense-python
Version: 1.17.0
Summary: GraphSense API
Author-email: Iknaio Cryptoasset Analytics GmbH <contact@ikna.io>
Maintainer-email: Iknaio Cryptoasset Analytics GmbH <contact@ikna.io>
Project-URL: Homepage, https://graphsense.github.io/
Project-URL: Source, https://github.com/graphsense/graphsense-REST/tree/master/clients/python
Project-URL: Changelog, https://github.com/graphsense/graphsense-REST/tree/master/CHANGELOG.md
Project-URL: Bug Tracker, https://github.com/graphsense/graphsense-rest/issues
Keywords: OpenAPI,OpenAPI-Generator,GraphSense API
Requires-Python: >=3.6
Requires-Dist: urllib3>=1.25.3
Requires-Dist: python-dateutil>=2.5.3
